[
  {
    "q": "Как выбрать пакет?",
    "a": "Пройдите квиз и ROI-калькулятор — получите рекомендацию и окупаемость."
  },
  {
    "q": "Что входит в работу?",
    "a": "Артефакты: BMC, CJM, Roadmap, Risk Matrix, BI, unit-экономика."
  },
  {
    "q": "Какие сроки?",
    "a": "Промежуточные эффекты за 4–8 недель, целевые — ≤ 6 месяцев."
  },
  {
    "q": "Как происходит внедрение?",
    "a": "Работа по ЖЦП: discovery → growth → scale → EOL, с governance и stage-gates."
  },
  {
    "q": "Кому принадлежат артефакты?",
    "a": "Все материалы остаются у клиента по NDA."
  }
]